py_pilecore-1.1.2.dist-info/licenses/LICENSE
pypilecore/__init__.py
pypilecore/_version.py
pypilecore/api.py
pypilecore/exceptions.py
pypilecore/plot_utils.py
pypilecore/utils.py
pypilecore/common/__init__.py
pypilecore/common/piles/__init__.py
pypilecore/common/piles/grid.py
pypilecore/common/piles/main.py
pypilecore/common/piles/type.py
pypilecore/common/piles/geometry/__init__.py
pypilecore/common/piles/geometry/main.py
pypilecore/common/piles/geometry/materials.py
pypilecore/common/piles/geometry/components/__init__.py
pypilecore/common/piles/geometry/components/common.py
pypilecore/common/piles/geometry/components/rectangle.py
pypilecore/common/piles/geometry/components/round.py
pypilecore/input/__init__.py
pypilecore/input/grouper_properties.py
pypilecore/input/multi_cpt.py
pypilecore/input/soil_properties.py
pypilecore/input/tension.py
pypilecore/results/__init__.py
pypilecore/results/cases_multi_cpt_results.py
pypilecore/results/grouper_result.py
pypilecore/results/load_settlement.py
pypilecore/results/post_processing.py
pypilecore/results/result_definitions.py
pypilecore/results/soil_properties.py
pypilecore/results/typing.py
pypilecore/results/compression/multi_cpt_results.py
pypilecore/results/compression/single_cpt_results.py
pypilecore/results/tension/multi_cpt_results.py
pypilecore/results/tension/single_cpt_results.py
pypilecore/viewers/__init__.py
pypilecore/viewers/viewer_cpt_group_results.py
pypilecore/viewers/viewer_cpt_results.py
pypilecore/viewers/viewer_cpt_results_plan_view.py
pypilecore/viewers/interactive_figures/__init__.py
pypilecore/viewers/interactive_figures/figure_cpt_group_results_versus_ptls.py
pypilecore/viewers/interactive_figures/figure_cpt_results_plan_view.py
pypilecore/viewers/interactive_figures/figure_cpt_results_versus_ptls.py
pypilecore/viewers/interactive_figures/utils.py
py_pilecore-1.1.2.dist-info/METADATA
py_pilecore-1.1.2.dist-info/WHEEL
py_pilecore-1.1.2.dist-info/top_level.txt
py_pilecore-1.1.2.dist-info/RECORD
