Metadata-Version: 2.4
Name: py-pilecore
Version: 1.1.2
Summary: Public python SDK for the CEMS PileCore web-API.
License: MIT License
Project-URL: repository, https://github.com/cemsbv/py-pilecore
Keywords: API,PileCore,CEMS,CRUX
Requires-Python: >=3.11
License-File: LICENSE
Requires-Dist: anywidget<0.10,>=0.9.18
Requires-Dist: cems-nuclei[client]<4,>=3.0.0
Requires-Dist: dash<4,>=3.0.2
Requires-Dist: ipywidgets<9,>=8.1.5
Requires-Dist: matplotlib<4,>=3.10.1
Requires-Dist: natsort<9,>=8.4.0
Requires-Dist: numpy<3,>=2.2.4
Requires-Dist: pandas<3,>=2.2.3
Requires-Dist: plotly-geo<2,>=1.0.0
Requires-Dist: plotly<7,>=6.0.1
Requires-Dist: pygef<0.12,>=0.11.0
Requires-Dist: scipy<2,>=1.15.2
Requires-Dist: shapely<3,>=2.1.0
Requires-Dist: tqdm[notebook]<5,>=4.67.1
Provides-Extra: test
Requires-Dist: coveralls; extra == "test"
Requires-Dist: pytest; extra == "test"
Requires-Dist: openapi-core; extra == "test"
Provides-Extra: docs
Requires-Dist: Sphinx==8.2.3; extra == "docs"
Requires-Dist: asteroid-sphinx-theme==0.0.3; extra == "docs"
Requires-Dist: ipython==9.1.0; extra == "docs"
Requires-Dist: sphinx-autodoc-typehints==3.1.0; extra == "docs"
Requires-Dist: sphinx_rtd_theme==3.0.2; extra == "docs"
Provides-Extra: lint
Requires-Dist: ansible-lint==25.1.3; extra == "lint"
Requires-Dist: black==25.1.0; extra == "lint"
Requires-Dist: cfn-lint==1.33.2; extra == "lint"
Requires-Dist: cpplint==2.0.0; extra == "lint"
Requires-Dist: flake8==7.1.2; extra == "lint"
Requires-Dist: isort==6.0.0; extra == "lint"
Requires-Dist: mypy==1.15.0; extra == "lint"
Requires-Dist: sqlfluff==3.3.1; extra == "lint"
Requires-Dist: yamllint==1.35.1; extra == "lint"
Requires-Dist: yq==3.4.3; extra == "lint"
Dynamic: license-file
